finance_arith_center_common.py
finance_arith_center_common-0.1.1.dist-info/METADATA
finance_arith_center_common-0.1.1.dist-info/WHEEL
finance_arith_center_common-0.1.1.dist-info/RECORD
