Metadata-Version: 2.1
Name: finance_arith_center_common
Version: 0.1.1
Summary: 
License: MIT
Author: dingzhenguo
Author-email: dingzhenguo@research.xbmail.com.cn
Requires-Python: >=3.12,<4.0
Classifier: License :: OSI Approved :: MIT License
Classifier: Programming Language :: Python :: 3
Classifier: Programming Language :: Python :: 3.12
Requires-Dist: grpcio (>=1.43.0,<2.0.0)
Requires-Dist: grpcio-tools (>=1.43.0,<2.0.0)
Requires-Dist: pandas (>=2.2.2,<3.0.0)
